cli.py
eventhub_cli-0.0.0.dist-info/METADATA
eventhub_cli-0.0.0.dist-info/WHEEL
eventhub_cli-0.0.0.dist-info/entry_points.txt
eventhub_cli-0.0.0.dist-info/top_level.txt
eventhub_cli-0.0.0.dist-info/RECORD
